geltea/notebook_options.py
geltea/utils.py
geltea-0.0.3.dist-info/DESCRIPTION.rst
geltea-0.0.3.dist-info/METADATA
geltea-0.0.3.dist-info/RECORD
geltea-0.0.3.dist-info/WHEEL
geltea-0.0.3.dist-info/metadata.json
geltea-0.0.3.dist-info/top_level.txt
