Metadata-Version: 2.0
Name: geltea
Version: 0.0.3
Summary: UNKNOWN
Home-page: https://github.com/jcshoekstra/mlutils
Author: Jelte Hoekstra
Author-email: UNKNOWN
License: MIT
Platform: UNKNOWN
Requires-Dist: matplotlib
Requires-Dist: numpy
Requires-Dist: pandas
Requires-Dist: seaborn
Requires-Dist: sklearn
